LICENSE
README.md
setup.py
CVE_2020_27838.egg-info/PKG-INFO
CVE_2020_27838.egg-info/SOURCES.txt
CVE_2020_27838.egg-info/dependency_links.txt
CVE_2020_27838.egg-info/entry_points.txt
CVE_2020_27838.egg-info/requires.txt
CVE_2020_27838.egg-info/top_level.txt
cve202027838/__init__.py
cve202027838/main.py
cve202027838/includes/__init__.py
cve202027838/includes/bot.py
cve202027838/includes/filereader.py
cve202027838/includes/scan.py
cve202027838/includes/writefile.py
cve202027838/utils/__init__.py
cve202027838/utils/configure.py
cve202027838/utils/const.py
cve202027838/utils/helpers.py
cve202027838/utils/status.py